components/__init__.py
components/auth/__init__.py
components/auth/cache.py
components/auth/component.py
components/auth/interfaces.py
components/auth/models.py
components/auth/repository.py
components/auth/service.py
components/common/__init__.py
components/common/cache/__init__.py
components/common/cache/component.py
components/common/cache/config.py
components/common/cache/strategy.py
components/common/database/__init__.py
components/common/database/component.py
components/common/database/config.py
components/common/database/models.py
components/common/database/pool.py
components/common/database/repository.py
components/common/logging/__init__.py
components/common/logging/component.py
components/common/logging/config.py
components/common/logging/formatter.py
components/common/models/__init__.py
components/common/models/base_models.py
components/common/service/__init__.py
components/common/service/base_service.py
components/payment/__init__.py
components/payment/component.py
components/payment/interfaces.py
components/payment/models.py
components/payment/repository.py
components/payment/service.py
components/user/__init__.py
components/user/component.py
components/user/interfaces.py
components/user/models.py
components/user/repository.py
components/user/service.py
framework/__init__.py
framework/cli.py
framework/core/__init__.py
framework/core/application.py
framework/core/config.py
framework/core/container.py
framework/core/dependency_resolver.py
framework/core/lifecycle.py
framework/core/middleware.py
framework/core/plugin.py
framework/interfaces/__init__.py
framework/interfaces/application.py
framework/interfaces/component.py
framework/interfaces/plugin.py
python_modular_framework-1.0.0.dist-info/licenses/LICENSE
test/__init__.py
test/components/__init__.py
test/components/circular_a.py
test/components/circular_b.py
tests/__init__.py
tests/conftest.py
tests/coverage_analysis.py
tests/coverage_config.py
tests/fixtures/__init__.py
tests/fixtures/test_utils.py
tests/fixtures/test_data/__init__.py
python_modular_framework-1.0.0.dist-info/METADATA
python_modular_framework-1.0.0.dist-info/WHEEL
python_modular_framework-1.0.0.dist-info/entry_points.txt
python_modular_framework-1.0.0.dist-info/top_level.txt
python_modular_framework-1.0.0.dist-info/RECORD
