Metadata-Version: 2.4
Name: python-modular-framework
Version: 1.0.0
Summary: 一个功能完整的Python模块化框架，支持组件化开发、依赖注入、中间件系统、插件机制等现代软件开发的核心特性
Home-page: https://github.com/python-modular-framework/python-modular-framework
Author: Python模块化框架开发团队
Author-email: Python模块化框架开发团队 <dev@python-modular-framework.org>
Maintainer-email: Python模块化框架开发团队 <dev@python-modular-framework.org>
License: MIT
Project-URL: Homepage, https://github.com/python-modular-framework/python-modular-framework
Project-URL: Documentation, https://python-modular-framework.readthedocs.io
Project-URL: Repository, https://github.com/python-modular-framework/python-modular-framework.git
Project-URL: Issues, https://github.com/python-modular-framework/python-modular-framework/issues
Project-URL: Changelog, https://github.com/python-modular-framework/python-modular-framework/blob/main/CHANGELOG.md
Keywords: framework,modular,dependency-injection,middleware,plugins
Classifier: Development Status :: 5 - Production/Stable
Classifier: Intended Audience :: Developers
Classifier: License :: OSI Approved :: MIT License
Classifier: Operating System :: OS Independent
Classifier: Programming Language :: Python :: 3
Classifier: Programming Language :: Python :: 3.8
Classifier: Programming Language :: Python :: 3.9
Classifier: Programming Language :: Python :: 3.10
Classifier: Programming Language :: Python :: 3.11
Classifier: Programming Language :: Python :: 3.12
Classifier: Topic :: Software Development :: Libraries :: Application Frameworks
Classifier: Topic :: Software Development :: Libraries :: Python Modules
Requires-Python: >=3.8
License-File: LICENSE
Requires-Dist: pydantic>=2.0.0
Requires-Dist: typing-extensions>=4.0.0
Requires-Dist: pyyaml>=6.0
Provides-Extra: dev
Requires-Dist: black>=23.0.0; extra == "dev"
Requires-Dist: flake8>=6.0.0; extra == "dev"
Requires-Dist: mypy>=1.0.0; extra == "dev"
Requires-Dist: pytest>=7.0.0; extra == "dev"
Requires-Dist: pytest-cov>=4.0.0; extra == "dev"
Requires-Dist: pytest-mock>=3.10.0; extra == "dev"
Requires-Dist: bandit>=1.7.0; extra == "dev"
Requires-Dist: safety>=2.0.0; extra == "dev"
Requires-Dist: sphinx>=6.0.0; extra == "dev"
Requires-Dist: sphinx-rtd-theme>=1.0.0; extra == "dev"
Requires-Dist: sphinx-autodoc-typehints>=1.20.0; extra == "dev"
Provides-Extra: redis
Requires-Dist: redis>=4.0.0; extra == "redis"
Provides-Extra: postgresql
Requires-Dist: psycopg2-binary>=2.9.0; extra == "postgresql"
Provides-Extra: mysql
Requires-Dist: pymysql>=1.0.0; extra == "mysql"
Provides-Extra: all
Requires-Dist: python-modular-framework[dev,mysql,postgresql,redis]; extra == "all"
Dynamic: author
Dynamic: home-page
Dynamic: license-file
Dynamic: requires-python
